meshagent/api/__init__.py
meshagent/api/chan.py
meshagent/api/client.py
meshagent/api/crdt.py
meshagent/api/entrypoint.js
meshagent/api/helpers.py
meshagent/api/http.py
meshagent/api/keys.py
meshagent/api/messaging.py
meshagent/api/oauth.py
meshagent/api/participant.py
meshagent/api/participant_token.py
meshagent/api/participant_token_test.py
meshagent/api/port_forward.py
meshagent/api/protocol.py
meshagent/api/protocol_test.py
meshagent/api/py.typed
meshagent/api/reasoning_schema.py
meshagent/api/room_server_client.py
meshagent/api/runtime.py
meshagent/api/runtime_test.py
meshagent/api/schema.py
meshagent/api/schema_document.py
meshagent/api/schema_document_test.py
meshagent/api/schema_registry.py
meshagent/api/schema_test.py
meshagent/api/schema_util.py
meshagent/api/service_template_test.py
meshagent/api/services.py
meshagent/api/sql.py
meshagent/api/sql_test.py
meshagent/api/token_test.py
meshagent/api/urls.py
meshagent/api/version.py
meshagent/api/webhooks.py
meshagent/api/websocket_protocol.py
meshagent/api/specs/service.py
meshagent_api-0.25.1.dist-info/licenses/LICENSE
meshagent_api-0.25.1.dist-info/METADATA
meshagent_api-0.25.1.dist-info/WHEEL
meshagent_api-0.25.1.dist-info/top_level.txt
meshagent_api-0.25.1.dist-info/RECORD
