Metadata-Version: 2.4
Name: meshagent-api
Version: 0.25.1
Summary: Python Server API for Meshagent
License-Expression: Apache-2.0
Project-URL: Documentation, https://docs.meshagent.com
Project-URL: Website, https://www.meshagent.com
Project-URL: Source, https://www.meshagent.com
Requires-Python: >=3.13
License-File: LICENSE
Requires-Dist: pyjwt~=2.10
Requires-Dist: aiohttp[speedups]~=3.13.0
Requires-Dist: jsonschema~=4.23
Requires-Dist: pycrdt~=0.12.26
Requires-Dist: opentelemetry-distro~=0.54b1
Requires-Dist: pydantic~=2.11.7
Requires-Dist: jinja2~=3.1.6
Requires-Dist: certifi~=2026.1.4
Provides-Extra: all
Provides-Extra: sync
Provides-Extra: stpyv8
Requires-Dist: stpyv8~=13.1; extra == "stpyv8"
Provides-Extra: ci
Requires-Dist: pytest~=8.4; extra == "ci"
Requires-Dist: pytest-asyncio~=0.26; extra == "ci"
Dynamic: license-file
